.gitlab-ci.yml
.travis.yml
CHANGES.rst
CONTRIBUTORS.rst
DEVELOP.rst
LICENSE.GPL
LICENSE.rst
MANIFEST.in
README.rst
constraints.txt
constraints_plone52.txt
constraints_plone60.txt
requirements.txt
requirements_plone52.txt
requirements_plone60.txt
setup.cfg
setup.py
tox.ini
docs/conf.py
docs/filters.xlsx
docs/index.rst
src/dsgov/__init__.py
src/dsgov.migration.egg-info/PKG-INFO
src/dsgov.migration.egg-info/SOURCES.txt
src/dsgov.migration.egg-info/dependency_links.txt
src/dsgov.migration.egg-info/entry_points.txt
src/dsgov.migration.egg-info/namespace_packages.txt
src/dsgov.migration.egg-info/not-zip-safe
src/dsgov.migration.egg-info/requires.txt
src/dsgov.migration.egg-info/top_level.txt
src/dsgov/migration/__init__.py
src/dsgov/migration/configure.zcml
src/dsgov/migration/interfaces.py
src/dsgov/migration/permissions.zcml
src/dsgov/migration/setuphandlers.py
src/dsgov/migration/testing.py
src/dsgov/migration/browser/__init__.py
src/dsgov/migration/browser/configure.zcml
src/dsgov/migration/browser/overrides/.gitkeep
src/dsgov/migration/browser/static/.gitkeep
src/dsgov/migration/importers/__init__.py
src/dsgov/migration/importers/blueprints.py
src/dsgov/migration/importers/configure.zcml
src/dsgov/migration/importers/import_content.cfg
src/dsgov/migration/importers/utils.py
src/dsgov/migration/locales/README.rst
src/dsgov/migration/locales/__init__.py
src/dsgov/migration/locales/dsgov.migration.pot
src/dsgov/migration/locales/update.py
src/dsgov/migration/locales/update.sh
src/dsgov/migration/locales/en/LC_MESSAGES/dsgov.migration.mo
src/dsgov/migration/locales/en/LC_MESSAGES/dsgov.migration.po
src/dsgov/migration/profiles/default/browserlayer.xml
src/dsgov/migration/profiles/default/catalog.xml
src/dsgov/migration/profiles/default/dsgov.migration-default.txt
src/dsgov/migration/profiles/default/metadata.xml
src/dsgov/migration/profiles/default/rolemap.xml
src/dsgov/migration/profiles/default/registry/main.xml
src/dsgov/migration/profiles/import_content/dsgov.migration-import_content.txt
src/dsgov/migration/profiles/import_content/transmogrifier.txt
src/dsgov/migration/profiles/uninstall/browserlayer.xml
src/dsgov/migration/tests/__init__.py
src/dsgov/migration/tests/test_robot.py
src/dsgov/migration/tests/test_setup.py
src/dsgov/migration/tests/robot/test_example.robot