Metadata-Version: 2.1
Name: dsgov.migration
Version: 1.0b3
Summary: A add-on to import json content to plone
Home-page: https://github.com/collective/dsgov.migration
Author: handryks@gmail.com
Author-email: handryks@gmail.com
License: GPL version 2
Project-URL: PyPI, https://pypi.python.org/pypi/dsgov.migration
Project-URL: Source, https://github.com/collective/dsgov.migration
Project-URL: Tracker, https://github.com/collective/dsgov.migration/issues
Keywords: Python Plone CMS
Platform: UNKNOWN
Classifier: Environment :: Web Environment
Classifier: Framework :: Plone
Classifier: Framework :: Plone :: Addon
Classifier: Framework :: Plone :: 5.2
Classifier: Framework :: Plone :: 6.0
Classifier: Programming Language :: Python
Classifier: Programming Language :: Python :: 3.7
Classifier: Programming Language :: Python :: 3.8
Classifier: Programming Language :: Python :: 3.9
Classifier: Operating System :: OS Independent
Classifier: License :: OSI Approved :: GNU General Public License v2 (GPLv2)
Requires-Python: >=3.7
Provides-Extra: test
License-File: LICENSE.GPL
License-File: LICENSE.rst
